connectmp/__init__.py
connectmp/connection.py
connectmp/settings.py
connectmp/core/__init__.py
connectmp/core/config.py
connectmp/core/db.py
connectmp/core/utils.py
connectmp/core/management/__init__.py
connectmp/core/management/commands.py
tests/__init__.py
tests/exceptions.py
tests/funcs.py
tests/test.py
connectmp-1.1.0.dist-info/LICENSE.md
connectmp-1.1.0.dist-info/METADATA
connectmp-1.1.0.dist-info/WHEEL
connectmp-1.1.0.dist-info/top_level.txt
connectmp-1.1.0.dist-info/RECORD
