Metadata-Version: 2.1
Name: connectmp
Version: 1.1.0
Summary: ConnectMP - The easiest and efficient way to share data between Processes. It's superfast, can handle big datas, cancreate `multiple` data connection and really simple to get started. 🍰
Home-page: https://github.com/AidenEllis/ConnectMP
Author: Aiden Ellis
Author-email: itsaidenellis@protonmail.com
License: MIT
Project-URL: Github, https://github.com/AidenEllis/ConnectMP
Project-URL: Documentation, https://github.com/ConnectMP/
Project-URL: Issue tracker, https://github.com/AidenEllis/ConnectMP/issues
Keywords: ConnectMP,process,data,sharing,multiprocessing,AidenEllis
Platform: UNKNOWN
Classifier: Development Status :: 5 - Production/Stable
Classifier: Programming Language :: Python :: 3
Classifier: Operating System :: OS Independent
Classifier: License :: OSI Approved :: MIT License
Classifier: Natural Language :: English
Classifier: Intended Audience :: Developers
Classifier: Topic :: Software Development :: Libraries
Classifier: Topic :: Software Development :: Libraries :: Python Modules
Classifier: Topic :: Utilities
License-File: LICENSE.md
Requires-Dist: certifi
Requires-Dist: greenlet
Requires-Dist: wincertstore
